[
  {
    "type": "feat",
    "scope": null,
    "subject": "Updated with new version of @pie-lib-config-ui. Renamed `configure` with `configuration`. Removed usage of state (root.jsx) and updated tests. (#225)",
    "merge": null,
    "header": "feat: Updated with new version of @pie-lib-config-ui. Renamed `configure` with `configuration`. Removed usage of state (root.jsx) and updated tests. (#225)",
    "body": null,
    "footer": "BREAKING CHANGE: `configure` is removed, use `configuration` instead.",
    "notes": [
      {
        "title": "BREAKING CHANGE",
        "text": "`configure` is removed, use `configuration` instead."
      }
    ],
    "hash": "380cdf9165fae6cc0e5f6940ab5ce6df25288206",
    "gitTags": "",
    "committerDate": "2019-05-15 13:04:28 -0400",
    "isTagged": true,
    "tag": "@pie-element/hotspot-configure@2.0.0"
  },
  {
    "type": "feat",
    "scope": "hotspot",
    "subject": "added rationale support.",
    "merge": null,
    "header": "feat(hotspot): added rationale support.",
    "body": null,
    "footer": null,
    "notes": [],
    "hash": "f60039aa487c5324195b9ca914f7156404f45b1d",
    "gitTags": "",
    "committerDate": "2019-05-11 17:44:54 +0300",
    "isTagged": true,
    "tag": "@pie-element/hotspot-configure@2.0.0"
  },
  {
    "type": "fix",
    "scope": null,
    "subject": "Handle the way model is changed from config layout [ch1621]",
    "merge": null,
    "header": "fix: Handle the way model is changed from config layout [ch1621]",
    "body": null,
    "footer": null,
    "notes": [],
    "hash": "2f979d05a14aec53066ee1a099783e7efc388563",
    "gitTags": "",
    "committerDate": "2019-05-16 20:51:05 +0300",
    "isTagged": true,
    "tag": "@pie-element/hotspot-configure@2.0.1"
  },
  {
    "type": "chore",
    "scope": "latest-version",
    "subject": "pushing to release",
    "merge": null,
    "header": "chore(latest-version): pushing to release",
    "body": null,
    "footer": null,
    "notes": [],
    "hash": "64030ba2c7c18d20381b6a0f5caaff19f1e5e959",
    "gitTags": " (develop)",
    "committerDate": "2019-06-06 01:31:17 +0300",
    "isTagged": true,
    "tag": "@pie-element/hotspot-configure@2.1.0"
  },
  {
    "type": "chore",
    "scope": "version",
    "subject": "bumped the versions",
    "merge": null,
    "header": "chore(version): bumped the versions",
    "body": null,
    "footer": null,
    "notes": [],
    "hash": "12b141d884c66a15d23c8cbb34be820a422d7332",
    "gitTags": " (origin/feat/mask-markup-elements)",
    "committerDate": "2019-06-06 01:15:50 +0300",
    "isTagged": true,
    "tag": "@pie-element/hotspot-configure@2.1.0"
  },
  {
    "type": "feat",
    "scope": null,
    "subject": "add support for polygons  (#246)",
    "merge": null,
    "header": "feat: add support for polygons  (#246)",
    "body": "* feat: add controller support for polygons\n\n* add tests for polygon\n\n* update Hotspot model",
    "footer": null,
    "notes": [],
    "hash": "871c5a6f033f36b2d172140cbbc0f71d59c8f969",
    "gitTags": "",
    "committerDate": "2019-05-31 14:03:05 -0400",
    "isTagged": true,
    "tag": "@pie-element/hotspot-configure@2.1.0"
  },
  {
    "type": "chore",
    "scope": "version",
    "subject": "bumped the packages that depend on the editable-html",
    "merge": null,
    "header": "chore(version): bumped the packages that depend on the editable-html",
    "body": null,
    "footer": null,
    "notes": [],
    "hash": "00eb12e58c01b50dde8e4d1a179c879e2f3216fc",
    "gitTags": " (develop)",
    "committerDate": "2019-06-06 13:16:05 +0300",
    "isTagged": true,
    "tag": "@pie-element/hotspot-configure@2.1.1"
  },
  {
    "type": "chore",
    "scope": "version",
    "subject": "bumped the versions",
    "merge": null,
    "header": "chore(version): bumped the versions",
    "body": null,
    "footer": null,
    "notes": [],
    "hash": "12b141d884c66a15d23c8cbb34be820a422d7332",
    "gitTags": " (origin/feat/mask-markup-elements)",
    "committerDate": "2019-06-06 01:15:50 +0300",
    "isTagged": true,
    "tag": "@pie-element/hotspot-configure@2.1.0"
  },
  {
    "type": "feat",
    "scope": null,
    "subject": "add support for polygons  (#246)",
    "merge": null,
    "header": "feat: add support for polygons  (#246)",
    "body": "* feat: add controller support for polygons\n\n* add tests for polygon\n\n* update Hotspot model",
    "footer": null,
    "notes": [],
    "hash": "871c5a6f033f36b2d172140cbbc0f71d59c8f969",
    "gitTags": "",
    "committerDate": "2019-05-31 14:03:05 -0400",
    "isTagged": true,
    "tag": "@pie-element/hotspot-configure@2.1.0"
  },
  {
    "type": "chore",
    "scope": "merge",
    "subject": "merged develop into master",
    "merge": null,
    "header": "chore(merge): merged develop into master",
    "body": null,
    "footer": null,
    "notes": [],
    "hash": "3bb9f402d900f3a0349537dfd01ce558c526cb55",
    "gitTags": " (develop)",
    "committerDate": "2019-06-07 23:29:44 +0300",
    "isTagged": true,
    "tag": "@pie-element/hotspot-configure@2.1.2"
  },
  {
    "type": "chore",
    "scope": "merged",
    "subject": "merged develop",
    "merge": null,
    "header": "chore(merged): merged develop",
    "body": null,
    "footer": null,
    "notes": [],
    "hash": "1a9f4653ce6ede22bcda0538bde1f0e09bd69dc4",
    "gitTags": " (develop)",
    "committerDate": "2019-06-13 16:26:43 +0300",
    "isTagged": true,
    "tag": "@pie-element/hotspot-configure@2.2.0"
  },
  {
    "type": "feat",
    "scope": null,
    "subject": "implement rendering support for legacy content with correct answers defined as polygon [ch1616]",
    "merge": null,
    "header": "feat: implement rendering support for legacy content with correct answers defined as polygon [ch1616]",
    "body": null,
    "footer": null,
    "notes": [],
    "hash": "d4b84e5d01caa600c27bab06ae11c827f3197992",
    "gitTags": "",
    "committerDate": "2019-06-12 17:31:35 +0300",
    "isTagged": true,
    "tag": "@pie-element/hotspot-configure@2.2.0"
  },
  {
    "type": "feat",
    "scope": "general",
    "subject": "updated all the packages that have the config-ui as a dependency",
    "merge": null,
    "header": "feat(general): updated all the packages that have the config-ui as a dependency",
    "body": null,
    "footer": null,
    "notes": [],
    "hash": "44061deecae6d18cdbf6f5fb524f3d3094ccd354",
    "gitTags": "",
    "committerDate": "2019-06-20 22:32:48 -0400",
    "isTagged": true,
    "tag": "@pie-element/hotspot-configure@2.3.0"
  },
  {
    "type": "feat",
    "scope": "settings-panel",
    "subject": "updated the settings panel design and changes needed for [ch2242]",
    "merge": null,
    "header": "feat(settings-panel): updated the settings panel design and changes needed for [ch2242]",
    "body": null,
    "footer": null,
    "notes": [],
    "hash": "d830e57b32bd09ac8cc02c7a12d75d988d9df21c",
    "gitTags": "",
    "committerDate": "2019-06-25 23:42:15 -0400",
    "isTagged": true,
    "tag": "@pie-element/hotspot-configure@2.4.0"
  },
  {
    "type": "feat",
    "scope": "mask-markup-elements",
    "subject": "refactored the elements and version bumped the necessary files",
    "merge": null,
    "header": "feat(mask-markup-elements): refactored the elements and version bumped the necessary files",
    "body": null,
    "footer": null,
    "notes": [],
    "hash": "f8f77c02e44afd90e491a371d86d3d4093eb41e5",
    "gitTags": "",
    "committerDate": "2019-07-02 13:38:48 -0400",
    "isTagged": true,
    "tag": "@pie-element/hotspot-configure@2.5.0"
  },
  {
    "type": "chore",
    "scope": "editable-html",
    "subject": "version bumped the necessary packages",
    "merge": null,
    "header": "chore(editable-html): version bumped the necessary packages",
    "body": null,
    "footer": null,
    "notes": [],
    "hash": "3c7caf6a1f8dc120ca23ab93258a90a593bbeb65",
    "gitTags": "",
    "committerDate": "2019-07-02 15:13:55 -0400",
    "isTagged": true,
    "tag": "@pie-element/hotspot-configure@2.5.1"
  },
  {
    "type": "chore",
    "scope": "version",
    "subject": "version bumped the editable-html dependent packages",
    "merge": null,
    "header": "chore(version): version bumped the editable-html dependent packages",
    "body": null,
    "footer": null,
    "notes": [],
    "hash": "19961d346e8596064bad27156e0cf5a03afc3889",
    "gitTags": "",
    "committerDate": "2019-07-03 15:57:58 -0400",
    "isTagged": true,
    "tag": "@pie-element/hotspot-configure@2.5.3"
  },
  {
    "type": "fix",
    "scope": "template-els",
    "subject": "fixed some ditb issues",
    "merge": null,
    "header": "fix(template-els): fixed some ditb issues",
    "body": null,
    "footer": null,
    "notes": [],
    "hash": "9133840e48a263b2cf49ce4db9c4310743efffe0",
    "gitTags": "",
    "committerDate": "2019-07-04 11:45:23 -0400",
    "isTagged": true,
    "tag": "@pie-element/hotspot-configure@2.5.4"
  },
  {
    "type": "fix",
    "scope": "editable-html",
    "subject": "fixed lots of stuff regarding the editable-html",
    "merge": null,
    "header": "fix(editable-html): fixed lots of stuff regarding the editable-html",
    "body": null,
    "footer": null,
    "notes": [],
    "hash": "12c112917e0b5065ec35efdbdc276703602a6c68",
    "gitTags": " (origin/andrei/fixes)",
    "committerDate": "2019-07-07 14:16:34 -0400",
    "isTagged": true,
    "tag": "@pie-element/hotspot-configure@2.5.6"
  },
  {
    "type": "chore",
    "scope": "config-ui",
    "subject": "bumped dependent packages",
    "merge": null,
    "header": "chore(config-ui): bumped dependent packages",
    "body": null,
    "footer": null,
    "notes": [],
    "hash": "645756c242868cf21e36a73227b355affb5f957a",
    "gitTags": "",
    "committerDate": "2019-07-07 15:44:44 -0400",
    "isTagged": true,
    "tag": "@pie-element/hotspot-configure@2.5.7"
  },
  {
    "type": "chore",
    "scope": "editable-html",
    "subject": "version bumped some dependant packages",
    "merge": null,
    "header": "chore(editable-html): version bumped some dependant packages",
    "body": null,
    "footer": null,
    "notes": [],
    "hash": "a4fbf3e8e7841ecae4f034328f9481a1f69ae3df",
    "gitTags": "",
    "committerDate": "2019-07-09 13:38:59 +0300",
    "isTagged": true,
    "tag": "@pie-element/hotspot-configure@2.5.8"
  },
  {
    "type": "feat",
    "scope": "template-elements",
    "subject": "updated the dependent packages that use editable-html and fixed [ch2564], [ch2565], [ch2538], [ch2489], [ch2557], [ch2593], [ch2490], [ch2527]",
    "merge": null,
    "header": "feat(template-elements): updated the dependent packages that use editable-html and fixed [ch2564], [ch2565], [ch2538], [ch2489], [ch2557], [ch2593], [ch2490], [ch2527]",
    "body": null,
    "footer": null,
    "notes": [],
    "hash": "a87febe2518ada7ee433b0b39895c26c15737ac4",
    "gitTags": "",
    "committerDate": "2019-07-11 16:57:13 +0300",
    "isTagged": true,
    "tag": "@pie-element/hotspot-configure@2.6.0"
  },
  {
    "type": "fix",
    "scope": "rendering",
    "subject": "implemented rendering for math elements [ch1915], [ch1935]",
    "merge": null,
    "header": "fix(rendering): implemented rendering for math elements [ch1915], [ch1935]",
    "body": null,
    "footer": null,
    "notes": [],
    "hash": "2f3584200654e098c7b4cc4b312813efac09e7a9",
    "gitTags": "",
    "committerDate": "2019-07-12 15:45:27 +0300",
    "isTagged": true,
    "tag": "@pie-element/hotspot-configure@2.6.2"
  },
  {
    "type": "feat",
    "scope": "hotspot",
    "subject": "universal prompt treatment",
    "merge": null,
    "header": "feat(hotspot): universal prompt treatment",
    "body": null,
    "footer": null,
    "notes": [],
    "hash": "a86bdc3717ef70df416c75392c69f1a163c46f5f",
    "gitTags": "",
    "committerDate": "2019-07-31 12:43:18 +0300",
    "isTagged": true,
    "tag": "@pie-element/hotspot-configure@2.7.0"
  },
  {
    "type": "fix",
    "scope": "elements",
    "subject": "version bumped the editable-html packages [ch1738]",
    "merge": null,
    "header": "fix(elements): version bumped the editable-html packages [ch1738]",
    "body": null,
    "footer": null,
    "notes": [],
    "hash": "949222a6a3af39cf8b81a885a81e5c6f3c6a28a0",
    "gitTags": "",
    "committerDate": "2019-08-08 08:40:11 +0300",
    "isTagged": true,
    "tag": "@pie-element/hotspot-configure@2.7.1"
  },
  {
    "type": "fix",
    "scope": "math-rendering",
    "subject": "updated all dependent packages [ch3365]",
    "merge": null,
    "header": "fix(math-rendering): updated all dependent packages [ch3365]",
    "body": null,
    "footer": null,
    "notes": [],
    "hash": "7cbf25ac92040a16621d5699e232c38575f6c36c",
    "gitTags": "",
    "committerDate": "2019-08-16 23:04:42 +0300",
    "isTagged": true,
    "tag": "@pie-element/hotspot-configure@2.7.2"
  },
  {
    "type": "fix",
    "scope": null,
    "subject": "set default values to configuration properties",
    "merge": null,
    "header": "fix: set default values to configuration properties",
    "body": null,
    "footer": null,
    "notes": [],
    "hash": "b5f84bbf1a91955535e63f3b276a8dc6b41d6594",
    "gitTags": "",
    "committerDate": "2019-08-15 13:57:30 +0300",
    "isTagged": true,
    "tag": "@pie-element/hotspot-configure@2.7.2"
  },
  {
    "type": "fix",
    "scope": "math-rendering",
    "subject": "updated all dependent packages for math rendering and for editable-html [ch3365], [ch1530]",
    "merge": null,
    "header": "fix(math-rendering): updated all dependent packages for math rendering and for editable-html [ch3365], [ch1530]",
    "body": null,
    "footer": null,
    "notes": [],
    "hash": "33e3287a735cec9aed893f697a1933ff0c077042",
    "gitTags": "",
    "committerDate": "2019-08-19 19:37:56 +0300",
    "isTagged": true,
    "tag": "@pie-element/hotspot-configure@2.7.3"
  },
  {
    "type": "fix",
    "scope": "hotspot",
    "subject": "hotspotList prop type is array, not string (#315)",
    "merge": null,
    "header": "fix(hotspot): hotspotList prop type is array, not string (#315)",
    "body": null,
    "footer": null,
    "notes": [],
    "hash": "4280a99a04bef043fd5267253e4bb115c70f2359",
    "gitTags": "",
    "committerDate": "2019-08-30 09:30:57 -0400",
    "isTagged": true,
    "tag": "@pie-element/hotspot-configure@2.7.7"
  },
  {
    "type": "feat",
    "scope": "drawable",
    "subject": "fixed the not rendering item preview [ch3629]",
    "merge": null,
    "header": "feat(drawable): fixed the not rendering item preview [ch3629]",
    "body": null,
    "footer": null,
    "notes": [],
    "hash": "9c7b05360ffd7c17cfaec34f8bbf5f5385dafc95",
    "gitTags": "",
    "committerDate": "2019-09-23 12:34:44 +0300",
    "isTagged": true,
    "tag": "@pie-element/hotspot-configure@3.1.0"
  },
  {
    "type": "feat",
    "scope": "hotspot",
    "subject": "model based prompt",
    "merge": null,
    "header": "feat(hotspot): model based prompt",
    "body": null,
    "footer": null,
    "notes": [],
    "hash": "2ff380b42245fd8296374b43ede6814d9c22bb34",
    "gitTags": "",
    "committerDate": "2019-09-24 15:56:36 +0300",
    "isTagged": true,
    "tag": "@pie-element/hotspot-configure@3.2.0"
  },
  {
    "type": "fix",
    "scope": null,
    "subject": "Hide Partial Scoring option from Settings Panel setting to false by default.",
    "merge": null,
    "header": "fix: Hide Partial Scoring option from Settings Panel setting to false by default.",
    "body": null,
    "footer": null,
    "notes": [],
    "hash": "1d0f617741d88756dd9861647981b1121e04963f",
    "gitTags": "",
    "committerDate": "2019-11-06 09:57:11 +0200",
    "isTagged": true,
    "tag": "@pie-element/hotspot-configure@4.0.2"
  },
  {
    "type": "feat",
    "scope": null,
    "subject": "added support for declared polygons (display them, possibility to mark/unmark as correct, possibility to drag/drop).",
    "merge": null,
    "header": "feat: added support for declared polygons (display them, possibility to mark/unmark as correct, possibility to drag/drop).",
    "body": null,
    "footer": null,
    "notes": [],
    "hash": "85d06039078128ccff7531c0f86297baf3b89e53",
    "gitTags": "",
    "committerDate": "2019-12-12 18:33:43 +0200",
    "isTagged": true,
    "tag": "@pie-element/hotspot-configure@4.1.0"
  },
  {
    "type": "fix",
    "scope": null,
    "subject": "ch2880: For some hotspot items, the distinction between selected and not selected areas is quite subtle (increased border width)",
    "merge": null,
    "header": "fix: ch2880: For some hotspot items, the distinction between selected and not selected areas is quite subtle (increased border width)",
    "body": null,
    "footer": null,
    "notes": [],
    "hash": "7769a154b4d54111d22fc866e03573813a0f7f1a",
    "gitTags": " (origin/andreea/ch2880/for-some-hotspot-items-the-distinction-between)",
    "committerDate": "2019-12-19 12:17:00 +0200",
    "isTagged": true,
    "tag": "@pie-element/hotspot-configure@4.1.2"
  },
  {
    "type": "fix",
    "scope": null,
    "subject": "ch7720: Authoring problem with Hotspot: Double-clicking image crashes Build screen",
    "merge": null,
    "header": "fix: ch7720: Authoring problem with Hotspot: Double-clicking image crashes Build screen",
    "body": null,
    "footer": null,
    "notes": [],
    "hash": "94f4e0782b0778860658a1bcde6d65493169e267",
    "gitTags": "",
    "committerDate": "2020-03-12 16:52:26 +0200",
    "isTagged": true,
    "tag": "@pie-element/hotspot-configure@4.2.0"
  },
  {
    "type": "fix",
    "scope": null,
    "subject": "bump ui versions",
    "merge": null,
    "header": "fix: bump ui versions",
    "body": null,
    "footer": null,
    "notes": [],
    "hash": "5b9d99fe59c304bdd173c9336503eb558900d2a2",
    "gitTags": "",
    "committerDate": "2020-03-31 19:25:13 +0100",
    "isTagged": true,
    "tag": "@pie-element/hotspot-configure@4.2.0"
  },
  {
    "type": "fix",
    "scope": null,
    "subject": "bump lib and ui versions",
    "merge": null,
    "header": "fix: bump lib and ui versions",
    "body": null,
    "footer": null,
    "notes": [],
    "hash": "a882cbf4580098ce0e12c51cf6ad2879817e17e7",
    "gitTags": "",
    "committerDate": "2020-04-10 17:13:24 +0100",
    "isTagged": true,
    "tag": "@pie-element/hotspot-configure@4.4.0"
  },
  {
    "type": "feat",
    "scope": null,
    "subject": "7727: When resizing images in hotspot, the default behavior should be to keep the aspect ratio fixed",
    "merge": null,
    "header": "feat: 7727: When resizing images in hotspot, the default behavior should be to keep the aspect ratio fixed",
    "body": null,
    "footer": null,
    "notes": [],
    "hash": "651d7e2e3d0f1c4f2bdf4089ca3437f547363648",
    "gitTags": "",
    "committerDate": "2020-03-30 16:00:49 +0300",
    "isTagged": true,
    "tag": "@pie-element/hotspot-configure@4.4.0"
  },
  {
    "type": "fix",
    "scope": null,
    "subject": "ch7799: the Item Preview for a legacy hot spot item appears to show the wrong answer because the lines that are too close to the margins are not visible. Solution: add padding and move content accordingly so that the lines will be displayed entirely.",
    "merge": null,
    "header": "fix: ch7799: the Item Preview for a legacy hot spot item appears to show the wrong answer because the lines that are too close to the margins are not visible. Solution: add padding and move content accordingly so that the lines will be displayed entirely.",
    "body": null,
    "footer": null,
    "notes": [],
    "hash": "a5c696e11115214ab3dee76461eff1c8dca98939",
    "gitTags": "",
    "committerDate": "2020-03-27 12:48:40 +0200",
    "isTagged": true,
    "tag": "@pie-element/hotspot-configure@4.4.0"
  },
  {
    "type": "fix",
    "scope": null,
    "subject": "bump all packages to avoid tag conflict",
    "merge": null,
    "header": "fix: bump all packages to avoid tag conflict",
    "body": null,
    "footer": null,
    "notes": [],
    "hash": "d9ec9a8689f0a391594b5e2f4ea958c6dc9f6d7b",
    "gitTags": "",
    "committerDate": "2020-04-10 20:01:37 +0100",
    "isTagged": true,
    "tag": "@pie-element/hotspot-configure@4.4.0"
  },
  {
    "type": "fix",
    "scope": null,
    "subject": "bump ui/lib versions",
    "merge": null,
    "header": "fix: bump ui/lib versions",
    "body": null,
    "footer": null,
    "notes": [],
    "hash": "3edb2321ebaefcaee70c3642aa6da8a50e8a99e5",
    "gitTags": "",
    "committerDate": "2020-04-14 15:36:44 +0100",
    "isTagged": true,
    "tag": "@pie-element/hotspot-configure@4.4.2"
  },
  {
    "type": "fix",
    "scope": null,
    "subject": "bump ui/lib versions",
    "merge": null,
    "header": "fix: bump ui/lib versions",
    "body": null,
    "footer": null,
    "notes": [],
    "hash": "45f0da6e3e01f33aff6059cb13d571554690348b",
    "gitTags": " (origin/develop, origin/HEAD, develop)",
    "committerDate": "2020-04-28 14:57:57 +0100",
    "isTagged": true,
    "tag": "@pie-element/hotspot-configure@4.4.3"
  },
  {
    "type": "fix",
    "scope": null,
    "subject": "update ui/lib versions",
    "merge": null,
    "header": "fix: update ui/lib versions",
    "body": null,
    "footer": null,
    "notes": [],
    "hash": "0226b0bc0869d468ba3e5986bc469e020f4f12a6",
    "gitTags": "",
    "committerDate": "2020-04-28 14:20:37 +0100",
    "isTagged": true,
    "tag": "@pie-element/hotspot-configure@4.4.3"
  },
  {
    "type": "fix",
    "scope": null,
    "subject": "ui+libs update",
    "merge": null,
    "header": "fix: ui+libs update",
    "body": null,
    "footer": null,
    "notes": [],
    "hash": "6127de27006a7835d1dd7a9c4c5f13de950aa06d",
    "gitTags": "",
    "committerDate": "2020-04-27 19:52:07 +0100",
    "isTagged": true,
    "tag": "@pie-element/hotspot-configure@4.4.3"
  },
  {
    "type": "fix",
    "scope": null,
    "subject": "PD-56: Bug with resizing an image in hot spot",
    "merge": null,
    "header": "fix: PD-56: Bug with resizing an image in hot spot",
    "body": "fix: PD-57: Hotspot: Enlarge the Help icon\nfix: PD-58: Hotspot: Hotspot creation should use a drag-and-drop gesture to create hotspots.",
    "footer": null,
    "notes": [],
    "hash": "bfeb160b80d089178b193b990d68b61965be8866",
    "gitTags": "",
    "committerDate": "2020-04-17 09:31:25 +0300",
    "isTagged": true,
    "tag": "@pie-element/hotspot-configure@4.4.3"
  }
]