{
  "description": "Model Object for @pie-elements/charting",
  "additionalProperties": false,
  "type": "object",
  "properties": {
    "addCategoryEnabled": {
      "description": "Indicates if user can add more categories",
      "type": "boolean",
      "title": "addCategoryEnabled"
    },
    "categoryDefaultLabel": {
      "description": "Indicates default value for a new category's label",
      "type": "string",
      "title": "categoryDefaultLabel"
    },
    "chartType": {
      "enum": [
        "bar",
        "dorPlot",
        "histogram",
        "lineCross",
        "lineDot",
        "linePlot"
      ],
      "type": "string",
      "title": "chartType"
    },
    "correctAnswer": {
      "title": "Answer",
      "type": "object",
      "properties": {
        "name": {
          "description": "Indicates name of answer",
          "type": "string",
          "title": "name"
        },
        "data": {
          "description": "Indicates marks for the answer",
          "type": "array",
          "items": [
            {
              "title": "Category",
              "type": "object",
              "properties": {
                "label": {
                  "description": "Indicates category label",
                  "type": "string",
                  "title": "label"
                },
                "value": {
                  "description": "Indicates category value",
                  "type": "number",
                  "title": "value"
                },
                "interactive": {
                  "description": "Indicates if category label & value are interactive",
                  "type": "boolean",
                  "title": "interactive"
                },
                "editable": {
                  "description": "Indicates if category label is editable",
                  "type": "boolean",
                  "title": "editable"
                },
                "deletable": {
                  "description": "Indicates if category is deletable",
                  "type": "boolean",
                  "title": "deletable"
                },
                "correctness": {
                  "description": "Indicates correctness for a category",
                  "type": "object",
                  "properties": {
                    "value": {
                      "enum": [
                        "correct",
                        "incorrect"
                      ],
                      "type": "string",
                      "title": "value"
                    },
                    "label": {
                      "enum": [
                        "correct",
                        "incorrect"
                      ],
                      "type": "string",
                      "title": "label"
                    }
                  },
                  "required": [
                    "label",
                    "value"
                  ],
                  "title": "correctness"
                }
              },
              "required": [
                "correctness",
                "deletable",
                "editable",
                "interactive",
                "label",
                "value"
              ]
            }
          ],
          "minItems": 1,
          "additionalItems": {
            "anyOf": [
              {
                "title": "Category",
                "type": "object",
                "properties": {
                  "label": {
                    "description": "Indicates category label",
                    "type": "string",
                    "title": "label"
                  },
                  "value": {
                    "description": "Indicates category value",
                    "type": "number",
                    "title": "value"
                  },
                  "interactive": {
                    "description": "Indicates if category label & value are interactive",
                    "type": "boolean",
                    "title": "interactive"
                  },
                  "editable": {
                    "description": "Indicates if category label is editable",
                    "type": "boolean",
                    "title": "editable"
                  },
                  "deletable": {
                    "description": "Indicates if category is deletable",
                    "type": "boolean",
                    "title": "deletable"
                  },
                  "correctness": {
                    "description": "Indicates correctness for a category",
                    "type": "object",
                    "properties": {
                      "value": {
                        "enum": [
                          "correct",
                          "incorrect"
                        ],
                        "type": "string",
                        "title": "value"
                      },
                      "label": {
                        "enum": [
                          "correct",
                          "incorrect"
                        ],
                        "type": "string",
                        "title": "label"
                      }
                    },
                    "required": [
                      "label",
                      "value"
                    ],
                    "title": "correctness"
                  }
                },
                "required": [
                  "correctness",
                  "deletable",
                  "editable",
                  "interactive",
                  "label",
                  "value"
                ]
              }
            ]
          },
          "title": "data"
        }
      },
      "required": [
        "data",
        "name"
      ]
    },
    "data": {
      "description": "Indicates default categories for the answer",
      "type": "array",
      "items": [
        {
          "title": "Category",
          "type": "object",
          "properties": {
            "label": {
              "description": "Indicates category label",
              "type": "string",
              "title": "label"
            },
            "value": {
              "description": "Indicates category value",
              "type": "number",
              "title": "value"
            },
            "interactive": {
              "description": "Indicates if category label & value are interactive",
              "type": "boolean",
              "title": "interactive"
            },
            "editable": {
              "description": "Indicates if category label is editable",
              "type": "boolean",
              "title": "editable"
            },
            "deletable": {
              "description": "Indicates if category is deletable",
              "type": "boolean",
              "title": "deletable"
            },
            "correctness": {
              "description": "Indicates correctness for a category",
              "type": "object",
              "properties": {
                "value": {
                  "enum": [
                    "correct",
                    "incorrect"
                  ],
                  "type": "string",
                  "title": "value"
                },
                "label": {
                  "enum": [
                    "correct",
                    "incorrect"
                  ],
                  "type": "string",
                  "title": "label"
                }
              },
              "required": [
                "label",
                "value"
              ],
              "title": "correctness"
            }
          },
          "required": [
            "correctness",
            "deletable",
            "editable",
            "interactive",
            "label",
            "value"
          ]
        }
      ],
      "minItems": 1,
      "additionalItems": {
        "anyOf": [
          {
            "title": "Category",
            "type": "object",
            "properties": {
              "label": {
                "description": "Indicates category label",
                "type": "string",
                "title": "label"
              },
              "value": {
                "description": "Indicates category value",
                "type": "number",
                "title": "value"
              },
              "interactive": {
                "description": "Indicates if category label & value are interactive",
                "type": "boolean",
                "title": "interactive"
              },
              "editable": {
                "description": "Indicates if category label is editable",
                "type": "boolean",
                "title": "editable"
              },
              "deletable": {
                "description": "Indicates if category is deletable",
                "type": "boolean",
                "title": "deletable"
              },
              "correctness": {
                "description": "Indicates correctness for a category",
                "type": "object",
                "properties": {
                  "value": {
                    "enum": [
                      "correct",
                      "incorrect"
                    ],
                    "type": "string",
                    "title": "value"
                  },
                  "label": {
                    "enum": [
                      "correct",
                      "incorrect"
                    ],
                    "type": "string",
                    "title": "label"
                  }
                },
                "required": [
                  "label",
                  "value"
                ],
                "title": "correctness"
              }
            },
            "required": [
              "correctness",
              "deletable",
              "editable",
              "interactive",
              "label",
              "value"
            ]
          }
        ]
      },
      "title": "data"
    },
    "domain": {
      "title": "ChartSettings",
      "type": "object",
      "properties": {
        "min": {
          "description": "Min value",
          "type": "number",
          "title": "min"
        },
        "max": {
          "description": "Max value",
          "type": "number",
          "title": "max"
        },
        "step": {
          "description": "Step value",
          "type": "number",
          "title": "step"
        },
        "labelStep": {
          "description": "Label step value",
          "type": "number",
          "title": "labelStep"
        },
        "axisLabel": {
          "description": "Axis Label",
          "type": "string",
          "title": "axisLabel"
        }
      },
      "required": [
        "axisLabel",
        "labelStep",
        "max",
        "min",
        "step"
      ]
    },
    "editCategoryEnabled": {
      "description": "Indicates if user can edit default categories",
      "type": "boolean",
      "title": "editCategoryEnabled"
    },
    "graph": {
      "title": "Chart",
      "type": "object",
      "properties": {
        "width": {
          "description": "Width for chart representation",
          "type": "number",
          "title": "width"
        },
        "height": {
          "description": "Height for chart representation",
          "type": "number",
          "title": "height"
        }
      },
      "required": [
        "height",
        "width"
      ]
    },
    "prompt": {
      "description": "Indicates prompt value",
      "type": "string",
      "title": "prompt"
    },
    "promptEnabled": {
      "description": "Indicates if the prompt is enabled",
      "type": "boolean",
      "title": "promptEnabled"
    },
    "range": {
      "title": "ChartSettings",
      "type": "object",
      "properties": {
        "min": {
          "description": "Min value",
          "type": "number",
          "title": "min"
        },
        "max": {
          "description": "Max value",
          "type": "number",
          "title": "max"
        },
        "step": {
          "description": "Step value",
          "type": "number",
          "title": "step"
        },
        "labelStep": {
          "description": "Label step value",
          "type": "number",
          "title": "labelStep"
        },
        "axisLabel": {
          "description": "Axis Label",
          "type": "string",
          "title": "axisLabel"
        }
      },
      "required": [
        "axisLabel",
        "labelStep",
        "max",
        "min",
        "step"
      ]
    },
    "rationale": {
      "description": "Indicates rationale for the answer",
      "type": "string",
      "title": "rationale"
    },
    "scoringType": {
      "description": "Indicates scoring type",
      "enum": [
        "all or nothing",
        "partial scoring"
      ],
      "type": "string",
      "title": "scoringType"
    },
    "studentInstructions": {
      "description": "Indicates student instructions",
      "type": "string",
      "title": "studentInstructions"
    },
    "teacherInstructions": {
      "description": "Indicates teacher instructions",
      "type": "string",
      "title": "teacherInstructions"
    },
    "title": {
      "description": "Indicates chart title",
      "type": "string",
      "title": "title"
    },
    "rationaleEnabled": {
      "description": "Indicates if Rationale are enabled",
      "type": "boolean",
      "title": "rationaleEnabled"
    },
    "spellCheckEnabled": {
      "description": "Indicates if spellcheck is enabled for the author. Default value is true",
      "type": "boolean",
      "title": "spellCheckEnabled"
    },
    "studentInstructionsEnabled": {
      "description": "Indicates if Student Instructions are enabled",
      "type": "boolean",
      "title": "studentInstructionsEnabled"
    },
    "teacherInstructionsEnabled": {
      "description": "Indicates if Teacher Instructions are enabled",
      "type": "boolean",
      "title": "teacherInstructionsEnabled"
    },
    "id": {
      "description": "Identifier to identify the Pie Element in html markup, Must be unique within a pie item config.",
      "type": "string",
      "title": "id"
    },
    "element": {
      "description": "The html Element tag name",
      "type": "string",
      "title": "element"
    }
  },
  "required": [
    "addCategoryEnabled",
    "categoryDefaultLabel",
    "chartType",
    "correctAnswer",
    "data",
    "domain",
    "editCategoryEnabled",
    "element",
    "graph",
    "id",
    "range",
    "rationaleEnabled",
    "spellCheckEnabled",
    "studentInstructionsEnabled",
    "teacherInstructionsEnabled"
  ],
  "definitions": {
    "ConfigureProp": {
      "title": "ConfigureProp",
      "type": "object",
      "properties": {
        "settings": {
          "description": "Indicates if the item has to be displayed in the Settings Panel",
          "type": "boolean",
          "title": "settings"
        },
        "label": {
          "description": "Indicates the label for the item that has to be displayed in the Settings Panel",
          "type": "string",
          "title": "label"
        }
      }
    },
    "ConfigurePropWithEnabled": {
      "title": "ConfigurePropWithEnabled",
      "type": "object",
      "properties": {
        "settings": {
          "description": "Indicates if the item has to be displayed in the Settings Panel",
          "type": "boolean",
          "title": "settings"
        },
        "label": {
          "description": "Indicates the label for the item that has to be displayed in the Settings Panel",
          "type": "string",
          "title": "label"
        },
        "enabled": {
          "description": "Indicates the value of the item if it affects config-ui\n(eg.: if item is a switch and displaying an input on the config-ui depends on the switch value: on/off)",
          "type": "boolean",
          "title": "enabled"
        }
      }
    },
    "Answer": {
      "title": "Answer",
      "type": "object",
      "properties": {
        "name": {
          "description": "Indicates name of answer",
          "type": "string",
          "title": "name"
        },
        "data": {
          "description": "Indicates marks for the answer",
          "type": "array",
          "items": [
            {
              "title": "Category",
              "type": "object",
              "properties": {
                "label": {
                  "description": "Indicates category label",
                  "type": "string",
                  "title": "label"
                },
                "value": {
                  "description": "Indicates category value",
                  "type": "number",
                  "title": "value"
                },
                "interactive": {
                  "description": "Indicates if category label & value are interactive",
                  "type": "boolean",
                  "title": "interactive"
                },
                "editable": {
                  "description": "Indicates if category label is editable",
                  "type": "boolean",
                  "title": "editable"
                },
                "deletable": {
                  "description": "Indicates if category is deletable",
                  "type": "boolean",
                  "title": "deletable"
                },
                "correctness": {
                  "description": "Indicates correctness for a category",
                  "type": "object",
                  "properties": {
                    "value": {
                      "enum": [
                        "correct",
                        "incorrect"
                      ],
                      "type": "string",
                      "title": "value"
                    },
                    "label": {
                      "enum": [
                        "correct",
                        "incorrect"
                      ],
                      "type": "string",
                      "title": "label"
                    }
                  },
                  "required": [
                    "label",
                    "value"
                  ],
                  "title": "correctness"
                }
              },
              "required": [
                "correctness",
                "deletable",
                "editable",
                "interactive",
                "label",
                "value"
              ]
            }
          ],
          "minItems": 1,
          "additionalItems": {
            "anyOf": [
              {
                "title": "Category",
                "type": "object",
                "properties": {
                  "label": {
                    "description": "Indicates category label",
                    "type": "string",
                    "title": "label"
                  },
                  "value": {
                    "description": "Indicates category value",
                    "type": "number",
                    "title": "value"
                  },
                  "interactive": {
                    "description": "Indicates if category label & value are interactive",
                    "type": "boolean",
                    "title": "interactive"
                  },
                  "editable": {
                    "description": "Indicates if category label is editable",
                    "type": "boolean",
                    "title": "editable"
                  },
                  "deletable": {
                    "description": "Indicates if category is deletable",
                    "type": "boolean",
                    "title": "deletable"
                  },
                  "correctness": {
                    "description": "Indicates correctness for a category",
                    "type": "object",
                    "properties": {
                      "value": {
                        "enum": [
                          "correct",
                          "incorrect"
                        ],
                        "type": "string",
                        "title": "value"
                      },
                      "label": {
                        "enum": [
                          "correct",
                          "incorrect"
                        ],
                        "type": "string",
                        "title": "label"
                      }
                    },
                    "required": [
                      "label",
                      "value"
                    ],
                    "title": "correctness"
                  }
                },
                "required": [
                  "correctness",
                  "deletable",
                  "editable",
                  "interactive",
                  "label",
                  "value"
                ]
              }
            ]
          },
          "title": "data"
        }
      },
      "required": [
        "data",
        "name"
      ]
    },
    "Category": {
      "title": "Category",
      "type": "object",
      "properties": {
        "label": {
          "description": "Indicates category label",
          "type": "string",
          "title": "label"
        },
        "value": {
          "description": "Indicates category value",
          "type": "number",
          "title": "value"
        },
        "interactive": {
          "description": "Indicates if category label & value are interactive",
          "type": "boolean",
          "title": "interactive"
        },
        "editable": {
          "description": "Indicates if category label is editable",
          "type": "boolean",
          "title": "editable"
        },
        "deletable": {
          "description": "Indicates if category is deletable",
          "type": "boolean",
          "title": "deletable"
        },
        "correctness": {
          "description": "Indicates correctness for a category",
          "type": "object",
          "properties": {
            "value": {
              "enum": [
                "correct",
                "incorrect"
              ],
              "type": "string",
              "title": "value"
            },
            "label": {
              "enum": [
                "correct",
                "incorrect"
              ],
              "type": "string",
              "title": "label"
            }
          },
          "required": [
            "label",
            "value"
          ],
          "title": "correctness"
        }
      },
      "required": [
        "correctness",
        "deletable",
        "editable",
        "interactive",
        "label",
        "value"
      ]
    },
    "ChartSettings": {
      "title": "ChartSettings",
      "type": "object",
      "properties": {
        "min": {
          "description": "Min value",
          "type": "number",
          "title": "min"
        },
        "max": {
          "description": "Max value",
          "type": "number",
          "title": "max"
        },
        "step": {
          "description": "Step value",
          "type": "number",
          "title": "step"
        },
        "labelStep": {
          "description": "Label step value",
          "type": "number",
          "title": "labelStep"
        },
        "axisLabel": {
          "description": "Axis Label",
          "type": "string",
          "title": "axisLabel"
        }
      },
      "required": [
        "axisLabel",
        "labelStep",
        "max",
        "min",
        "step"
      ]
    },
    "Chart": {
      "title": "Chart",
      "type": "object",
      "properties": {
        "width": {
          "description": "Width for chart representation",
          "type": "number",
          "title": "width"
        },
        "height": {
          "description": "Height for chart representation",
          "type": "number",
          "title": "height"
        }
      },
      "required": [
        "height",
        "width"
      ]
    }
  },
  "$schema": "http://json-schema.org/draft-07/schema#"
}